{
  "processId": 10315084,
  "status": "FINISHED",
  "content": {
    "text": "on a cellular basis. The study also included a dissection and silicon injection of a bonito, Sarda\nchiliensis, an ectothermic species in the same family as the tuna, for comparison.\nOnce the caecum blood supply was mapped out and the presence of a countercurrent heat\nexchangers was determined in yellowfin and blackfin tuna, the extent of heat production was\nassessed by enzymatic study. To determine the tissue metabolic capacity of the caecum, citrate\nsynthase (CS) activity was assayed. Citrate synthase, the rate limiting factor for the citric acid\ncycle, is considered an enzymatic marker for aerobic metabolism. Heater tissues of scombroid\nfish typically exhibit high levels aerobic activity (Tullis et al., 1991). Since metabolic activity\nproduces heat, it may be possible to gauge relative heat production according to CS activity. For\ncomparison, CS activity in another visceral organ, the liver, was measured. What resulted was a\npicture of the caecum as a site of countercurrent heat exchange within the yellowfin\nMaterials and Methods\nFour yellowfin tuna, referred to as YFTI, YFT2, YFT3, and YFT4, and two bonito, were\nobtained from the Tuna Research and Conservation Center in Monterey, California. Deaths\noccurred either from anesthesia or by pithing. Yellowfin and bonito used for dissection/injection\nwere either fresh or previously frozen.\nTwo blackfin tuna, were caught on longline in the Gulf of Mexico and frozen before\ndissection.\nSilicon Injections\nInjections were performed using Microfil injection compounds MV-120 (blue), MV-130\n(red) and MV-117 (orange). Components were mixed in a 5 (color): 4 (diluent): 1 (catalyst)\nratio. Curing time was approximately twenty minutes depending on the core temperature of each\nfish and the ambient temperature in the lab.\nThe desired vessels were first found through dissection. A catheter attached to a Cole-\nPamer three-way stopcock was inserted as far as possible into the vessel of choice and the\nsystem was flushed with sea water in order to rinse out blood and test for leaks or blockages.",
    "regions": [
      {
        "id": "tr_1",
        "coords": {
          "points": "298,289 298,2983 2285,2983 2285,289"
        },
        "orientation": 0.0,
        "lines": [
          {
            "id": "tr_1_tl_1",
            "coords": {
              "points": "287,386 1660,351 2160,396 2263,346 2214,267 2122,294 1999,250 1408,304 1168,299 1081,250 799,304 700,247 287,314"
            },
            "baseline": {
              "points": "301,352 399,349 497,346 595,346 694,346 792,346 890,346 989,343 1087,344 1185,343 1284,340 1382,340 1480,341 1578,340 1677,340 1775,340 1873,339 1972,337 2070,339 2168,337 2267,337"
            },
            "text": "on a cellular basis. The study also included a dissection and silicon injection of a bonito, Sarda",
            "words": [
              {
                "id": "tr_1_tl_1_w1",
                "coords": {
                  "points": "290,311 290,371 328,371 328,311"
                },
                "text": "on"
              },
              {
                "id": "tr_1_tl_1_w2",
                "coords": {
                  "points": "361,309 361,369 374,369 374,309"
                },
                "text": "a"
              },
              {
                "id": "tr_1_tl_1_w3",
                "coords": {
                  "points": "394,306 394,366 543,366 543,306"
                },
                "text": "cellular"
              },
              {
                "id": "tr_1_tl_1_w4",
                "coords": {
                  "points": "557,306 557,366 675,366 675,306"
                },
                "text": "basis."
              },
              {
                "id": "tr_1_tl_1_w5",
                "coords": {
                  "points": "702,306 702,366 773,366 773,306"
                },
                "text": "The"
              },
              {
                "id": "tr_1_tl_1_w6",
                "coords": {
                  "points": "800,306 800,366 897,366 897,306"
                },
                "text": "study"
              },
              {
                "id": "tr_1_tl_1_w7",
                "coords": {
                  "points": "924,303 924,363 989,363 989,303"
                },
                "text": "also"
              },
              {
                "id": "tr_1_tl_1_w8",
                "coords": {
                  "points": "1016,303 1016,363 1178,363 1178,303"
                },
                "text": "included"
              },
              {
                "id": "tr_1_tl_1_w9",
                "coords": {
                  "points": "1205,302 1205,362 1217,362 1217,302"
                },
                "text": "a"
              },
              {
                "id": "tr_1_tl_1_w10",
                "coords": {
                  "points": "1244,300 1244,360 1434,360 1434,300"
                },
                "text": "dissection"
              },
              {
                "id": "tr_1_tl_1_w11",
                "coords": {
                  "points": "1461,300 1461,360 1518,360 1518,300"
                },
                "text": "and"
              },
              {
                "id": "tr_1_tl_1_w12",
                "coords": {
                  "points": "1545,300 1545,360 1669,360 1669,300"
                },
                "text": "silicon"
              },
              {
                "id": "tr_1_tl_1_w13",
                "coords": {
                  "points": "1696,299 1696,359 1859,359 1859,299"
                },
                "text": "injection"
              },
              {
                "id": "tr_1_tl_1_w14",
                "coords": {
                  "points": "1886,298 1886,358 1924,358 1924,298"
                },
                "text": "of"
              },
              {
                "id": "tr_1_tl_1_w15",
                "coords": {
                  "points": "1945,297 1945,357 1958,357 1958,297"
                },
                "text": "a"
              },
              {
                "id": "tr_1_tl_1_w16",
                "coords": {
                  "points": "1978,298 1978,358 2121,358 2121,298"
                },
                "text": "bonito,"
              },
              {
                "id": "tr_1_tl_1_w17",
                "coords": {
                  "points": "2135,297 2135,357 2245,357 2245,297"
                },
                "text": "Sarda"
              }
            ]
          },
          {
            "id": "tr_1_tl_2",
            "coords": {
              "points": "287,468 1930,468 1930,386 1724,408 1613,366 1393,408 287,406"
            },
            "baseline": {
              "points": "301,450 382,447 464,450 546,447 628,445 709,446 791,444 873,443 955,444 1036,441 1118,441 1200,441 1282,440 1363,440 1445,441 1527,441 1609,439 1690,438 1772,438 1854,438 1936,438"
            },
            "text": "chiliensis, an ectothermic species in the same family as the tuna, for comparison.",
            "words": [
              {
                "id": "tr_1_tl_2_w1",
                "coords": {
                  "points": "294,407 294,467 496,467 496,407"
                },
                "text": "chiliensis,"
              },
              {
                "id": "tr_1_tl_2_w2",
                "coords": {
                  "points": "508,407 508,467 543,467 543,407"
                },
                "text": "an"
              },
              {
                "id": "tr_1_tl_2_w3",
                "coords": {
                  "points": "573,405 573,465 799,465 799,405"
                },
                "text": "ectothermic"
              },
              {
                "id": "tr_1_tl_2_w4",
                "coords": {
                  "points": "823,403 823,463 961,463 961,403"
                },
                "text": "species"
              },
              {
                "id": "tr_1_tl_2_w5",
                "coords": {
                  "points": "985,402 985,462 1008,462 1008,402"
                },
                "text": "in"
              },
              {
                "id": "tr_1_tl_2_w6",
                "coords": {
                  "points": "1032,401 1032,461 1084,461 1084,401"
                },
                "text": "the"
              },
              {
                "id": "tr_1_tl_2_w7",
                "coords": {
                  "points": "1108,401 1108,461 1200,461 1200,401"
                },
                "text": "same"
              },
              {
                "id": "tr_1_tl_2_w8",
                "coords": {
                  "points": "1230,400 1230,460 1345,460 1345,400"
                },
                "text": "family"
              },
              {
                "id": "tr_1_tl_2_w9",
                "coords": {
                  "points": "1375,400 1375,460 1403,460 1403,400"
                },
                "text": "as"
              },
              {
                "id": "tr_1_tl_2_w10",
                "coords": {
                  "points": "1427,401 1427,461 1479,461 1479,401"
                },
                "text": "the"
              },
              {
                "id": "tr_1_tl_2_w11",
                "coords": {
                  "points": "1503,400 1503,460 1601,460 1601,400"
                },
                "text": "tuna,"
              },
              {
                "id": "tr_1_tl_2_w12",
                "coords": {
                  "points": "1613,398 1613,458 1665,458 1665,398"
                },
                "text": "for"
              },
              {
                "id": "tr_1_tl_2_w13",
                "coords": {
                  "points": "1683,398 1683,458 1932,458 1932,398"
                },
                "text": "comparison."
              }
            ]
          },
          {
            "id": "tr_1_tl_3",
            "coords": {
              "points": "443,559 999,596 1202,557 1284,599 1346,554 1469,586 2266,559 2266,490 2150,480 1353,512 1284,470 1128,515 987,472 443,472"
            },
            "baseline": {
              "points": "456,548 546,547 637,546 728,545 819,544 910,544 1001,543 1091,543 1182,543 1273,544 1364,541 1455,541 1546,540 1637,540 1727,538 1818,540 1909,537 2000,537 2091,537 2182,537 2273,534"
            },
            "text": "Once the caecum blood supply was mapped out and the presence of a countercurrent heat",
            "words": [
              {
                "id": "tr_1_tl_3_w1",
                "coords": {
                  "points": "451,507 451,567 542,567 542,507"
                },
                "text": "Once"
              },
              {
                "id": "tr_1_tl_3_w2",
                "coords": {
                  "points": "568,506 568,566 622,566 622,506"
                },
                "text": "the"
              },
              {
                "id": "tr_1_tl_3_w3",
                "coords": {
                  "points": "642,505 642,565 770,565 770,505"
                },
                "text": "caecum"
              },
              {
                "id": "tr_1_tl_3_w4",
                "coords": {
                  "points": "815,504 815,564 912,564 912,504"
                },
                "text": "blood"
              },
              {
                "id": "tr_1_tl_3_w5",
                "coords": {
                  "points": "938,503 938,563 1060,563 1060,503"
                },
                "text": "supply"
              },
              {
                "id": "tr_1_tl_3_w6",
                "coords": {
                  "points": "1085,503 1085,563 1158,563 1158,503"
                },
                "text": "was"
              },
              {
                "id": "tr_1_tl_3_w7",
                "coords": {
                  "points": "1178,503 1178,563 1325,563 1325,503"
                },
                "text": "mapped"
              },
              {
                "id": "tr_1_tl_3_w8",
                "coords": {
                  "points": "1351,501 1351,561 1411,561 1411,501"
                },
                "text": "out"
              },
              {
                "id": "tr_1_tl_3_w9",
                "coords": {
                  "points": "1431,500 1431,560 1491,560 1491,500"
                },
                "text": "and"
              },
              {
                "id": "tr_1_tl_3_w10",
                "coords": {
                  "points": "1517,500 1517,560 1566,560 1566,500"
                },
                "text": "the"
              },
              {
                "id": "tr_1_tl_3_w11",
                "coords": {
                  "points": "1591,499 1591,559 1757,559 1757,499"
                },
                "text": "presence"
              },
              {
                "id": "tr_1_tl_3_w12",
                "coords": {
                  "points": "1782,499 1782,559 1818,559 1818,499"
                },
                "text": "of"
              },
              {
                "id": "tr_1_tl_3_w13",
                "coords": {
                  "points": "1837,499 1837,559 1849,559 1849,499"
                },
                "text": "a"
              },
              {
                "id": "tr_1_tl_3_w14",
                "coords": {
                  "points": "1868,497 1868,557 2157,557 2157,497"
                },
                "text": "countercurrent"
              },
              {
                "id": "tr_1_tl_3_w15",
                "coords": {
                  "points": "2176,495 2176,555 2256,555 2256,495"
                },
                "text": "heat"
              }
            ]
          },
          {
            "id": "tr_1_tl_4",
            "coords": {
              "points": "287,688 2261,656 2261,601 2093,581 1534,611 856,579 564,616 453,566 289,609"
            },
            "baseline": {
              "points": "304,647 402,649 500,645 598,644 696,644 794,644 892,644 991,644 1089,644 1187,644 1285,641 1383,641 1481,641 1579,641 1678,638 1776,638 1874,638 1972,638 2070,638 2168,636 2267,638"
            },
            "text": "exchangers was determined in yellowfin and blackfin tuna, the extent of heat production was",
            "words": [
              {
                "id": "tr_1_tl_4_w1",
                "coords": {
                  "points": "295,608 295,668 517,668 517,608"
                },
                "text": "exchangers"
              },
              {
                "id": "tr_1_tl_4_w2",
                "coords": {
                  "points": "542,604 542,664 613,664 613,604"
                },
                "text": "was"
              },
              {
                "id": "tr_1_tl_4_w3",
                "coords": {
                  "points": "638,604 638,664 855,664 855,604"
                },
                "text": "determined"
              },
              {
                "id": "tr_1_tl_4_w4",
                "coords": {
                  "points": "886,604 886,664 916,664 916,604"
                },
                "text": "in"
              },
              {
                "id": "tr_1_tl_4_w5",
                "coords": {
                  "points": "941,604 941,664 1128,664 1128,604"
                },
                "text": "yellowfin"
              },
              {
                "id": "tr_1_tl_4_w6",
                "coords": {
                  "points": "1159,603 1159,663 1218,663 1218,603"
                },
                "text": "and"
              },
              {
                "id": "tr_1_tl_4_w7",
                "coords": {
                  "points": "1249,601 1249,661 1405,661 1405,601"
                },
                "text": "blackfin"
              },
              {
                "id": "tr_1_tl_4_w8",
                "coords": {
                  "points": "1436,601 1436,661 1532,661 1532,601"
                },
                "text": "tuna,"
              },
              {
                "id": "tr_1_tl_4_w9",
                "coords": {
                  "points": "1551,601 1551,661 1605,661 1605,601"
                },
                "text": "the"
              },
              {
                "id": "tr_1_tl_4_w10",
                "coords": {
                  "points": "1636,598 1636,658 1756,658 1756,598"
                },
                "text": "extent"
              },
              {
                "id": "tr_1_tl_4_w11",
                "coords": {
                  "points": "1774,598 1774,658 1816,658 1816,598"
                },
                "text": "of"
              },
              {
                "id": "tr_1_tl_4_w12",
                "coords": {
                  "points": "1835,598 1835,658 1919,658 1919,598"
                },
                "text": "heat"
              },
              {
                "id": "tr_1_tl_4_w13",
                "coords": {
                  "points": "1938,598 1938,658 2148,658 2148,598"
                },
                "text": "production"
              },
              {
                "id": "tr_1_tl_4_w14",
                "coords": {
                  "points": "2179,596 2179,656 2251,656 2251,596"
                },
                "text": "was"
              }
            ]
          },
          {
            "id": "tr_1_tl_5",
            "coords": {
              "points": "284,762 359,801 616,757 881,804 987,754 1551,750 1734,794 1865,750 1917,782 2261,762 2261,685 284,688"
            },
            "baseline": {
              "points": "298,748 396,745 494,745 593,747 691,747 790,745 888,744 987,744 1085,742 1184,742 1282,742 1380,742 1479,741 1577,742 1676,741 1774,739 1873,739 1971,739 2070,739 2168,737 2267,739"
            },
            "text": "assessed by enzymatic study. To determine the tissue metabolic capacity of the caecum, citrate",
            "words": [
              {
                "id": "tr_1_tl_5_w1",
                "coords": {
                  "points": "285,705 285,765 445,765 445,705"
                },
                "text": "assessed"
              },
              {
                "id": "tr_1_tl_5_w2",
                "coords": {
                  "points": "475,705 475,765 516,765 516,705"
                },
                "text": "by"
              },
              {
                "id": "tr_1_tl_5_w3",
                "coords": {
                  "points": "540,707 540,767 742,767 742,707"
                },
                "text": "enzymatic"
              },
              {
                "id": "tr_1_tl_5_w4",
                "coords": {
                  "points": "767,704 767,764 890,764 890,704"
                },
                "text": "study."
              },
              {
                "id": "tr_1_tl_5_w5",
                "coords": {
                  "points": "915,704 915,764 962,764 962,704"
                },
                "text": "To"
              },
              {
                "id": "tr_1_tl_5_w6",
                "coords": {
                  "points": "992,702 992,762 1182,762 1182,702"
                },
                "text": "determine"
              },
              {
                "id": "tr_1_tl_5_w7",
                "coords": {
                  "points": "1206,702 1206,762 1259,762 1259,702"
                },
                "text": "the"
              },
              {
                "id": "tr_1_tl_5_w8",
                "coords": {
                  "points": "1283,702 1283,762 1390,762 1390,702"
                },
                "text": "tissue"
              },
              {
                "id": "tr_1_tl_5_w9",
                "coords": {
                  "points": "1414,701 1414,761 1610,761 1610,701"
                },
                "text": "metabolic"
              },
              {
                "id": "tr_1_tl_5_w10",
                "coords": {
                  "points": "1634,700 1634,760 1788,760 1788,700"
                },
                "text": "capacity"
              },
              {
                "id": "tr_1_tl_5_w11",
                "coords": {
                  "points": "1818,699 1818,759 1853,759 1853,699"
                },
                "text": "of"
              },
              {
                "id": "tr_1_tl_5_w12",
                "coords": {
                  "points": "1872,699 1872,759 1925,759 1925,699"
                },
                "text": "the"
              },
              {
                "id": "tr_1_tl_5_w13",
                "coords": {
                  "points": "1949,699 1949,759 2115,759 2115,699"
                },
                "text": "caecum,"
              },
              {
                "id": "tr_1_tl_5_w14",
                "coords": {
                  "points": "2133,697 2133,757 2251,757 2251,697"
                },
                "text": "citrate"
              }
            ]
          },
          {
            "id": "tr_1_tl_6",
            "coords": {
              "points": "284,881 967,883 1049,846 1239,886 1576,848 2266,876 2266,789 2209,779 284,804"
            },
            "baseline": {
              "points": "298,850 396,847 495,847 594,845 693,844 791,844 890,847 989,844 1088,844 1186,844 1285,844 1384,844 1483,841 1581,841 1680,841 1779,841 1878,838 1976,838 2075,838 2174,838 2273,838"
            },
            "text": "synthase (CS) activity was assayed. Citrate synthase, the rate limiting factor for the citric acid",
            "words": [
              {
                "id": "tr_1_tl_6_w1",
                "coords": {
                  "points": "286,807 286,867 453,867 453,807"
                },
                "text": "synthase"
              },
              {
                "id": "tr_1_tl_6_w2",
                "coords": {
                  "points": "479,806 479,866 575,866 575,806"
                },
                "text": "(CS)"
              },
              {
                "id": "tr_1_tl_6_w3",
                "coords": {
                  "points": "595,804 595,864 736,864 736,804"
                },
                "text": "activity"
              },
              {
                "id": "tr_1_tl_6_w4",
                "coords": {
                  "points": "763,804 763,864 832,864 832,804"
                },
                "text": "was"
              },
              {
                "id": "tr_1_tl_6_w5",
                "coords": {
                  "points": "859,805 859,865 1025,865 1025,805"
                },
                "text": "assayed."
              },
              {
                "id": "tr_1_tl_6_w6",
                "coords": {
                  "points": "1058,804 1058,864 1187,864 1187,804"
                },
                "text": "Citrate"
              },
              {
                "id": "tr_1_tl_6_w7",
                "coords": {
                  "points": "1213,804 1213,864 1399,864 1399,804"
                },
                "text": "synthase,"
              },
              {
                "id": "tr_1_tl_6_w8",
                "coords": {
                  "points": "1419,802 1419,862 1469,862 1469,802"
                },
                "text": "the"
              },
              {
                "id": "tr_1_tl_6_w9",
                "coords": {
                  "points": "1497,801 1497,861 1560,861 1560,801"
                },
                "text": "rate"
              },
              {
                "id": "tr_1_tl_6_w10",
                "coords": {
                  "points": "1586,801 1586,861 1740,861 1740,801"
                },
                "text": "limiting"
              },
              {
                "id": "tr_1_tl_6_w11",
                "coords": {
                  "points": "1766,799 1766,859 1882,859 1882,799"
                },
                "text": "factor"
              },
              {
                "id": "tr_1_tl_6_w12",
                "coords": {
                  "points": "1902,798 1902,858 1953,858 1953,798"
                },
                "text": "for"
              },
              {
                "id": "tr_1_tl_6_w13",
                "coords": {
                  "points": "1973,798 1973,858 2023,858 2023,798"
                },
                "text": "the"
              },
              {
                "id": "tr_1_tl_6_w14",
                "coords": {
                  "points": "2050,798 2050,858 2145,858 2145,798"
                },
                "text": "citric"
              },
              {
                "id": "tr_1_tl_6_w15",
                "coords": {
                  "points": "2172,798 2172,858 2248,858 2248,798"
                },
                "text": "acid"
              }
            ]
          },
          {
            "id": "tr_1_tl_7",
            "coords": {
              "points": "292,982 1410,952 1650,992 1727,950 2108,950 2239,985 2271,881 294,910"
            },
            "baseline": {
              "points": "307,948 405,948 503,947 602,945 700,945 799,945 897,945 996,945 1094,943 1193,943 1291,942 1389,942 1488,939 1586,939 1685,939 1783,939 1882,939 1980,936 2079,936 2177,937 2276,936"
            },
            "text": "cycle, is considered an enzymatic marker for aerobic metabolism. Heater tissues of scombroid",
            "words": [
              {
                "id": "tr_1_tl_7_w1",
                "coords": {
                  "points": "300,908 300,968 416,968 416,908"
                },
                "text": "cycle,"
              },
              {
                "id": "tr_1_tl_7_w2",
                "coords": {
                  "points": "435,907 435,967 459,967 459,907"
                },
                "text": "is"
              },
              {
                "id": "tr_1_tl_7_w3",
                "coords": {
                  "points": "484,905 484,965 693,965 693,905"
                },
                "text": "considered"
              },
              {
                "id": "tr_1_tl_7_w4",
                "coords": {
                  "points": "718,905 718,965 754,965 754,905"
                },
                "text": "an"
              },
              {
                "id": "tr_1_tl_7_w5",
                "coords": {
                  "points": "786,905 786,965 982,965 982,905"
                },
                "text": "enzymatic"
              },
              {
                "id": "tr_1_tl_7_w6",
                "coords": {
                  "points": "1007,903 1007,963 1148,963 1148,903"
                },
                "text": "marker"
              },
              {
                "id": "tr_1_tl_7_w7",
                "coords": {
                  "points": "1167,902 1167,962 1221,962 1221,902"
                },
                "text": "for"
              },
              {
                "id": "tr_1_tl_7_w8",
                "coords": {
                  "points": "1241,902 1241,962 1381,962 1381,902"
                },
                "text": "aerobic"
              },
              {
                "id": "tr_1_tl_7_w9",
                "coords": {
                  "points": "1407,899 1407,959 1652,959 1652,899"
                },
                "text": "metabolism."
              },
              {
                "id": "tr_1_tl_7_w10",
                "coords": {
                  "points": "1683,899 1683,959 1818,959 1818,899"
                },
                "text": "Heater"
              },
              {
                "id": "tr_1_tl_7_w11",
                "coords": {
                  "points": "1837,898 1837,958 1965,958 1965,898"
                },
                "text": "tissues"
              },
              {
                "id": "tr_1_tl_7_w12",
                "coords": {
                  "points": "1985,896 1985,956 2021,956 2021,896"
                },
                "text": "of"
              },
              {
                "id": "tr_1_tl_7_w13",
                "coords": {
                  "points": "2046,896 2046,956 2248,956 2248,896"
                },
                "text": "scombroid"
              }
            ]
          },
          {
            "id": "tr_1_tl_8",
            "coords": {
              "points": "284,1071 2261,1061 2263,980 2100,1012 1952,977 1509,1009 1076,972 1032,1014 287,985"
            },
            "baseline": {
              "points": "298,1047 396,1047 494,1047 593,1045 691,1044 790,1047 888,1044 987,1044 1085,1044 1184,1042 1282,1041 1380,1041 1479,1041 1577,1039 1676,1040 1774,1038 1873,1038 1971,1037 2070,1037 2168,1036 2267,1038"
            },
            "text": "fish typically exhibit high levels aerobic activity (Tullis et al., 1991). Since metabolic activity",
            "words": [
              {
                "id": "tr_1_tl_8_w1",
                "coords": {
                  "points": "292,1007 292,1067 348,1067 348,1007"
                },
                "text": "fish"
              },
              {
                "id": "tr_1_tl_8_w2",
                "coords": {
                  "points": "381,1007 381,1067 550,1067 550,1007"
                },
                "text": "typically"
              },
              {
                "id": "tr_1_tl_8_w3",
                "coords": {
                  "points": "576,1004 576,1064 714,1064 714,1004"
                },
                "text": "exhibit"
              },
              {
                "id": "tr_1_tl_8_w4",
                "coords": {
                  "points": "734,1006 734,1066 815,1066 815,1006"
                },
                "text": "high"
              },
              {
                "id": "tr_1_tl_8_w5",
                "coords": {
                  "points": "841,1004 841,1064 954,1064 954,1004"
                },
                "text": "levels"
              },
              {
                "id": "tr_1_tl_8_w6",
                "coords": {
                  "points": "973,1004 973,1064 1111,1064 1111,1004"
                },
                "text": "aerobic"
              },
              {
                "id": "tr_1_tl_8_w7",
                "coords": {
                  "points": "1137,1001 1137,1061 1282,1061 1282,1001"
                },
                "text": "activity"
              },
              {
                "id": "tr_1_tl_8_w8",
                "coords": {
                  "points": "1308,1001 1308,1061 1439,1061 1439,1001"
                },
                "text": "(Tullis"
              },
              {
                "id": "tr_1_tl_8_w9",
                "coords": {
                  "points": "1459,1001 1459,1061 1496,1061 1496,1001"
                },
                "text": "et"
              },
              {
                "id": "tr_1_tl_8_w10",
                "coords": {
                  "points": "1516,999 1516,1059 1578,1059 1578,999"
                },
                "text": "al.,"
              },
              {
                "id": "tr_1_tl_8_w11",
                "coords": {
                  "points": "1598,999 1598,1059 1729,1059 1729,999"
                },
                "text": "1991)."
              },
              {
                "id": "tr_1_tl_8_w12",
                "coords": {
                  "points": "1755,998 1755,1058 1862,1058 1862,998"
                },
                "text": "Since"
              },
              {
                "id": "tr_1_tl_8_w13",
                "coords": {
                  "points": "1888,997 1888,1057 2076,1057 2076,997"
                },
                "text": "metabolic"
              },
              {
                "id": "tr_1_tl_8_w14",
                "coords": {
                  "points": "2102,996 2102,1056 2246,1056 2246,996"
                },
                "text": "activity"
              }
            ]
          },
          {
            "id": "tr_1_tl_9",
            "coords": {
              "points": "284,1192 1662,1148 1791,1202 1920,1143 2266,1150 2266,1101 2098,1079 287,1108"
            },
            "baseline": {
              "points": "301,1154 399,1148 498,1148 596,1148 695,1145 794,1145 892,1145 991,1145 1089,1145 1188,1143 1287,1142 1385,1142 1484,1139 1582,1139 1681,1139 1780,1139 1878,1138 1977,1138 2075,1136 2174,1136 2273,1136"
            },
            "text": "produces heat, it may be possible to gauge relative heat production according to CS activity. For",
            "words": [
              {
                "id": "tr_1_tl_9_w1",
                "coords": {
                  "points": "287,1109 287,1169 467,1169 467,1109"
                },
                "text": "produces"
              },
              {
                "id": "tr_1_tl_9_w2",
                "coords": {
                  "points": "488,1108 488,1168 584,1168 584,1108"
                },
                "text": "heat,"
              },
              {
                "id": "tr_1_tl_9_w3",
                "coords": {
                  "points": "599,1107 599,1167 619,1167 619,1107"
                },
                "text": "it"
              },
              {
                "id": "tr_1_tl_9_w4",
                "coords": {
                  "points": "641,1105 641,1165 716,1165 716,1105"
                },
                "text": "may"
              },
              {
                "id": "tr_1_tl_9_w5",
                "coords": {
                  "points": "738,1105 738,1165 778,1165 778,1105"
                },
                "text": "be"
              },
              {
                "id": "tr_1_tl_9_w6",
                "coords": {
                  "points": "800,1105 800,1165 952,1165 952,1105"
                },
                "text": "possible"
              },
              {
                "id": "tr_1_tl_9_w7",
                "coords": {
                  "points": "980,1105 980,1165 1007,1165 1007,1105"
                },
                "text": "to"
              },
              {
                "id": "tr_1_tl_9_w8",
                "coords": {
                  "points": "1029,1105 1029,1165 1139,1165 1139,1105"
                },
                "text": "gauge"
              },
              {
                "id": "tr_1_tl_9_w9",
                "coords": {
                  "points": "1167,1102 1167,1162 1305,1162 1305,1102"
                },
                "text": "relative"
              },
              {
                "id": "tr_1_tl_9_w10",
                "coords": {
                  "points": "1326,1102 1326,1162 1409,1162 1409,1102"
                },
                "text": "heat"
              },
              {
                "id": "tr_1_tl_9_w11",
                "coords": {
                  "points": "1423,1099 1423,1159 1630,1159 1630,1099"
                },
                "text": "production"
              },
              {
                "id": "tr_1_tl_9_w12",
                "coords": {
                  "points": "1659,1099 1659,1159 1845,1159 1845,1099"
                },
                "text": "according"
              },
              {
                "id": "tr_1_tl_9_w13",
                "coords": {
                  "points": "1874,1098 1874,1158 1894,1158 1894,1098"
                },
                "text": "to"
              },
              {
                "id": "tr_1_tl_9_w14",
                "coords": {
                  "points": "1922,1098 1922,1158 1970,1158 1970,1098"
                },
                "text": "CS"
              },
              {
                "id": "tr_1_tl_9_w15",
                "coords": {
                  "points": "1998,1096 1998,1156 2157,1156 2157,1096"
                },
                "text": "activity."
              },
              {
                "id": "tr_1_tl_9_w16",
                "coords": {
                  "points": "2185,1096 2185,1156 2254,1156 2254,1096"
                },
                "text": "For"
              }
            ]
          },
          {
            "id": "tr_1_tl_10",
            "coords": {
              "points": "289,1267 685,1299 745,1267 1242,1294 1455,1249 1526,1284 2266,1257 2266,1197 2051,1173 1981,1210 1593,1170 1469,1212 289,1197"
            },
            "baseline": {
              "points": "304,1247 402,1249 500,1250 599,1247 697,1247 796,1247 894,1247 993,1246 1091,1244 1190,1244 1288,1244 1386,1243 1485,1242 1583,1241 1682,1241 1780,1241 1879,1239 1977,1240 2076,1240 2174,1238 2273,1241"
            },
            "text": "comparison, CS activity in another visceral organ, the liver, was measured. What resulted was a",
            "words": [
              {
                "id": "tr_1_tl_10_w1",
                "coords": {
                  "points": "290,1209 290,1269 539,1269 539,1209"
                },
                "text": "comparison,"
              },
              {
                "id": "tr_1_tl_10_w2",
                "coords": {
                  "points": "552,1207 552,1267 598,1267 598,1207"
                },
                "text": "CS"
              },
              {
                "id": "tr_1_tl_10_w3",
                "coords": {
                  "points": "627,1207 627,1267 766,1267 766,1207"
                },
                "text": "activity"
              },
              {
                "id": "tr_1_tl_10_w4",
                "coords": {
                  "points": "797,1207 797,1267 825,1267 825,1207"
                },
                "text": "in"
              },
              {
                "id": "tr_1_tl_10_w5",
                "coords": {
                  "points": "849,1206 849,1266 994,1266 994,1206"
                },
                "text": "another"
              },
              {
                "id": "tr_1_tl_10_w6",
                "coords": {
                  "points": "1018,1204 1018,1264 1168,1264 1168,1204"
                },
                "text": "visceral"
              },
              {
                "id": "tr_1_tl_10_w7",
                "coords": {
                  "points": "1186,1204 1186,1264 1314,1264 1314,1204"
                },
                "text": "organ,"
              },
              {
                "id": "tr_1_tl_10_w8",
                "coords": {
                  "points": "1326,1203 1326,1263 1378,1263 1378,1203"
                },
                "text": "the"
              },
              {
                "id": "tr_1_tl_10_w9",
                "coords": {
                  "points": "1402,1202 1402,1262 1506,1262 1506,1202"
                },
                "text": "liver,"
              },
              {
                "id": "tr_1_tl_10_w10",
                "coords": {
                  "points": "1524,1201 1524,1261 1593,1261 1593,1201"
                },
                "text": "was"
              },
              {
                "id": "tr_1_tl_10_w11",
                "coords": {
                  "points": "1617,1201 1617,1261 1821,1261 1821,1201"
                },
                "text": "measured."
              },
              {
                "id": "tr_1_tl_10_w12",
                "coords": {
                  "points": "1850,1199 1850,1259 1954,1259 1954,1199"
                },
                "text": "What"
              },
              {
                "id": "tr_1_tl_10_w13",
                "coords": {
                  "points": "1972,1200 1972,1260 2123,1260 2123,1200"
                },
                "text": "resulted"
              },
              {
                "id": "tr_1_tl_10_w14",
                "coords": {
                  "points": "2147,1198 2147,1258 2216,1258 2216,1198"
                },
                "text": "was"
              },
              {
                "id": "tr_1_tl_10_w15",
                "coords": {
                  "points": "2240,1200 2240,1260 2251,1260 2251,1200"
                },
                "text": "a"
              }
            ]
          },
          {
            "id": "tr_1_tl_11",
            "coords": {
              "points": "287,1413 470,1361 685,1410 895,1363 942,1400 1331,1351 1427,1395 2004,1368 2004,1306 1850,1272 1709,1309 1489,1274 1435,1311 824,1279 287,1314"
            },
            "baseline": {
              "points": "301,1360 386,1349 471,1348 557,1348 642,1348 728,1348 813,1348 899,1345 984,1345 1070,1345 1155,1345 1240,1345 1326,1343 1411,1342 1497,1342 1582,1341 1668,1342 1753,1342 1839,1339 1924,1339 2010,1339"
            },
            "text": "picture of the caecum as a site of countercurrent heat exchange within the yellowfin",
            "words": [
              {
                "id": "tr_1_tl_11_w1",
                "coords": {
                  "points": "297,1312 297,1372 428,1372 428,1312"
                },
                "text": "picture"
              },
              {
                "id": "tr_1_tl_11_w2",
                "coords": {
                  "points": "450,1308 450,1368 490,1368 490,1308"
                },
                "text": "of"
              },
              {
                "id": "tr_1_tl_11_w3",
                "coords": {
                  "points": "505,1308 505,1368 553,1368 553,1308"
                },
                "text": "the"
              },
              {
                "id": "tr_1_tl_11_w4",
                "coords": {
                  "points": "581,1308 581,1368 706,1368 706,1308"
                },
                "text": "caecum"
              },
              {
                "id": "tr_1_tl_11_w5",
                "coords": {
                  "points": "749,1308 749,1368 782,1368 782,1308"
                },
                "text": "as"
              },
              {
                "id": "tr_1_tl_11_w6",
                "coords": {
                  "points": "804,1308 804,1368 817,1368 817,1308"
                },
                "text": "a"
              },
              {
                "id": "tr_1_tl_11_w7",
                "coords": {
                  "points": "839,1306 839,1366 900,1366 900,1306"
                },
                "text": "site"
              },
              {
                "id": "tr_1_tl_11_w8",
                "coords": {
                  "points": "922,1305 922,1365 963,1365 963,1305"
                },
                "text": "of"
              },
              {
                "id": "tr_1_tl_11_w9",
                "coords": {
                  "points": "978,1305 978,1365 1268,1365 1268,1305"
                },
                "text": "countercurrent"
              },
              {
                "id": "tr_1_tl_11_w10",
                "coords": {
                  "points": "1283,1303 1283,1363 1366,1363 1366,1303"
                },
                "text": "heat"
              },
              {
                "id": "tr_1_tl_11_w11",
                "coords": {
                  "points": "1381,1302 1381,1362 1560,1362 1560,1302"
                },
                "text": "exchange"
              },
              {
                "id": "tr_1_tl_11_w12",
                "coords": {
                  "points": "1589,1301 1589,1361 1700,1361 1700,1301"
                },
                "text": "within"
              },
              {
                "id": "tr_1_tl_11_w13",
                "coords": {
                  "points": "1728,1302 1728,1362 1776,1362 1776,1302"
                },
                "text": "the"
              },
              {
                "id": "tr_1_tl_11_w14",
                "coords": {
                  "points": "1805,1299 1805,1359 1984,1359 1984,1299"
                },
                "text": "yellowfin"
              }
            ]
          },
          {
            "id": "tr_1_tl_12",
            "coords": {
              "points": "994,1477 1051,1499 1267,1474 1323,1497 1356,1474 1561,1482 1561,1403 1494,1417 1442,1393 1343,1398 1279,1420 1242,1388 1138,1417 994,1398"
            },
            "baseline": {
              "points": "1008,1461 1035,1461 1063,1459 1091,1457 1119,1456 1147,1456 1175,1456 1203,1456 1231,1456 1259,1456 1287,1456 1314,1455 1342,1453 1370,1453 1398,1453 1426,1453 1454,1453 1482,1453 1510,1455 1538,1456 1566,1456"
            },
            "text": "Materials and Methods",
            "words": [
              {
                "id": "tr_1_tl_12_w1",
                "coords": {
                  "points": "998,1416 998,1476 1214,1476 1214,1416"
                },
                "text": "Materials"
              },
              {
                "id": "tr_1_tl_12_w2",
                "coords": {
                  "points": "1244,1416 1244,1476 1315,1476 1315,1416"
                },
                "text": "and"
              },
              {
                "id": "tr_1_tl_12_w3",
                "coords": {
                  "points": "1345,1413 1345,1473 1547,1473 1547,1413"
                },
                "text": "Methods"
              }
            ]
          },
          {
            "id": "tr_1_tl_13",
            "coords": {
              "points": "435,1571 512,1608 826,1571 957,1615 1178,1568 1242,1605 1319,1566 2266,1578 2266,1516 1994,1442 1865,1516 1761,1477 1610,1519 1304,1492 1076,1526 435,1494"
            },
            "baseline": {
              "points": "450,1560 541,1557 632,1557 723,1557 814,1558 905,1557 996,1557 1088,1557 1179,1555 1270,1556 1361,1554 1452,1554 1543,1554 1634,1554 1726,1554 1817,1552 1908,1551 1999,1551 2090,1551 2181,1551 2273,1551"
            },
            "text": "Four yellowfin tuna, referred to as YFTI, YFT2, YFT3, and YFT4, and two bonito, were",
            "words": [
              {
                "id": "tr_1_tl_13_w1",
                "coords": {
                  "points": "437,1518 437,1578 533,1578 533,1518"
                },
                "text": "Four"
              },
              {
                "id": "tr_1_tl_13_w2",
                "coords": {
                  "points": "553,1517 553,1577 733,1577 733,1517"
                },
                "text": "yellowfin"
              },
              {
                "id": "tr_1_tl_13_w3",
                "coords": {
                  "points": "759,1517 759,1577 855,1577 855,1517"
                },
                "text": "tuna,"
              },
              {
                "id": "tr_1_tl_13_w4",
                "coords": {
                  "points": "875,1517 875,1577 1023,1577 1023,1517"
                },
                "text": "referred"
              },
              {
                "id": "tr_1_tl_13_w5",
                "coords": {
                  "points": "1050,1517 1050,1577 1075,1577 1075,1517"
                },
                "text": "to"
              },
              {
                "id": "tr_1_tl_13_w6",
                "coords": {
                  "points": "1102,1516 1102,1576 1133,1576 1133,1516"
                },
                "text": "as"
              },
              {
                "id": "tr_1_tl_13_w7",
                "coords": {
                  "points": "1160,1515 1160,1575 1288,1575 1288,1515"
                },
                "text": "YFTI,"
              },
              {
                "id": "tr_1_tl_13_w8",
                "coords": {
                  "points": "1308,1514 1308,1574 1436,1574 1436,1514"
                },
                "text": "YFT2,"
              },
              {
                "id": "tr_1_tl_13_w9",
                "coords": {
                  "points": "1456,1514 1456,1574 1584,1574 1584,1514"
                },
                "text": "YFT3,"
              },
              {
                "id": "tr_1_tl_13_w10",
                "coords": {
                  "points": "1598,1514 1598,1574 1655,1574 1655,1514"
                },
                "text": "and"
              },
              {
                "id": "tr_1_tl_13_w11",
                "coords": {
                  "points": "1689,1513 1689,1573 1817,1573 1817,1513"
                },
                "text": "YFT4,"
              },
              {
                "id": "tr_1_tl_13_w12",
                "coords": {
                  "points": "1830,1511 1830,1571 1894,1571 1894,1511"
                },
                "text": "and"
              },
              {
                "id": "tr_1_tl_13_w13",
                "coords": {
                  "points": "1920,1511 1920,1571 1984,1571 1984,1511"
                },
                "text": "two"
              },
              {
                "id": "tr_1_tl_13_w14",
                "coords": {
                  "points": "2004,1511 2004,1571 2152,1571 2152,1511"
                },
                "text": "bonito,"
              },
              {
                "id": "tr_1_tl_13_w15",
                "coords": {
                  "points": "2165,1511 2165,1571 2248,1571 2248,1511"
                },
                "text": "were"
              }
            ]
          },
          {
            "id": "tr_1_tl_14",
            "coords": {
              "points": "294,1707 1081,1667 1272,1712 1445,1670 1712,1699 1855,1657 2266,1692 2266,1596 2053,1618 1977,1578 1798,1618 1279,1588 1037,1628 750,1591 673,1628 294,1625"
            },
            "baseline": {
              "points": "307,1658 405,1661 503,1660 601,1658 700,1658 798,1658 896,1656 995,1658 1093,1656 1191,1655 1290,1655 1388,1655 1486,1655 1584,1655 1683,1653 1781,1652 1879,1652 1978,1652 2076,1652 2174,1652 2273,1649"
            },
            "text": "obtained from the Tuna Research and Conservation Center in Monterey, California. Deaths",
            "words": [
              {
                "id": "tr_1_tl_14_w1",
                "coords": {
                  "points": "302,1620 302,1680 464,1680 464,1620"
                },
                "text": "obtained"
              },
              {
                "id": "tr_1_tl_14_w2",
                "coords": {
                  "points": "495,1619 495,1679 566,1679 566,1619"
                },
                "text": "from"
              },
              {
                "id": "tr_1_tl_14_w3",
                "coords": {
                  "points": "615,1618 615,1678 663,1678 663,1618"
                },
                "text": "the"
              },
              {
                "id": "tr_1_tl_14_w4",
                "coords": {
                  "points": "694,1618 694,1678 790,1678 790,1618"
                },
                "text": "Tuna"
              },
              {
                "id": "tr_1_tl_14_w5",
                "coords": {
                  "points": "821,1616 821,1676 995,1676 995,1616"
                },
                "text": "Research"
              },
              {
                "id": "tr_1_tl_14_w6",
                "coords": {
                  "points": "1026,1616 1026,1676 1091,1676 1091,1616"
                },
                "text": "and"
              },
              {
                "id": "tr_1_tl_14_w7",
                "coords": {
                  "points": "1122,1615 1122,1675 1381,1675 1381,1615"
                },
                "text": "Conservation"
              },
              {
                "id": "tr_1_tl_14_w8",
                "coords": {
                  "points": "1412,1615 1412,1675 1544,1675 1544,1615"
                },
                "text": "Center"
              },
              {
                "id": "tr_1_tl_14_w9",
                "coords": {
                  "points": "1569,1615 1569,1675 1598,1675 1598,1615"
                },
                "text": "in"
              },
              {
                "id": "tr_1_tl_14_w10",
                "coords": {
                  "points": "1623,1612 1623,1672 1840,1672 1840,1612"
                },
                "text": "Monterey,"
              },
              {
                "id": "tr_1_tl_14_w11",
                "coords": {
                  "points": "1858,1612 1858,1672 2081,1672 2081,1612"
                },
                "text": "California."
              },
              {
                "id": "tr_1_tl_14_w12",
                "coords": {
                  "points": "2118,1611 2118,1671 2256,1671 2256,1611"
                },
                "text": "Deaths"
              }
            ]
          },
          {
            "id": "tr_1_tl_15",
            "coords": {
              "points": "297,1784 826,1813 878,1776 1200,1803 1281,1769 1608,1813 1722,1764 2273,1761 2273,1697 2231,1690 297,1727"
            },
            "baseline": {
              "points": "310,1760 408,1760 506,1757 604,1758 703,1760 801,1760 899,1758 998,1759 1096,1757 1194,1757 1293,1754 1391,1754 1489,1756 1587,1754 1686,1754 1784,1754 1882,1751 1981,1753 2079,1751 2177,1751 2276,1754"
            },
            "text": "occurred either from anesthesia or by pithing. Yellowfin and bonito used for dissection/injection",
            "words": [
              {
                "id": "tr_1_tl_15_w1",
                "coords": {
                  "points": "303,1720 303,1780 466,1780 466,1720"
                },
                "text": "occurred"
              },
              {
                "id": "tr_1_tl_15_w2",
                "coords": {
                  "points": "490,1717 490,1777 602,1777 602,1717"
                },
                "text": "either"
              },
              {
                "id": "tr_1_tl_15_w3",
                "coords": {
                  "points": "620,1719 620,1779 693,1779 693,1719"
                },
                "text": "from"
              },
              {
                "id": "tr_1_tl_15_w4",
                "coords": {
                  "points": "733,1719 733,1779 930,1779 930,1719"
                },
                "text": "anesthesia"
              },
              {
                "id": "tr_1_tl_15_w5",
                "coords": {
                  "points": "954,1718 954,1778 993,1778 993,1718"
                },
                "text": "or"
              },
              {
                "id": "tr_1_tl_15_w6",
                "coords": {
                  "points": "1010,1718 1010,1778 1043,1778 1043,1718"
                },
                "text": "by"
              },
              {
                "id": "tr_1_tl_15_w7",
                "coords": {
                  "points": "1072,1717 1072,1777 1224,1777 1224,1717"
                },
                "text": "pithing."
              },
              {
                "id": "tr_1_tl_15_w8",
                "coords": {
                  "points": "1253,1714 1253,1774 1445,1774 1445,1714"
                },
                "text": "Yellowfin"
              },
              {
                "id": "tr_1_tl_15_w9",
                "coords": {
                  "points": "1468,1715 1468,1775 1529,1775 1529,1715"
                },
                "text": "and"
              },
              {
                "id": "tr_1_tl_15_w10",
                "coords": {
                  "points": "1553,1714 1553,1774 1671,1774 1671,1714"
                },
                "text": "bonito"
              },
              {
                "id": "tr_1_tl_15_w11",
                "coords": {
                  "points": "1700,1714 1700,1774 1773,1774 1773,1714"
                },
                "text": "used"
              },
              {
                "id": "tr_1_tl_15_w12",
                "coords": {
                  "points": "1801,1712 1801,1772 1857,1772 1857,1712"
                },
                "text": "for"
              },
              {
                "id": "tr_1_tl_15_w13",
                "coords": {
                  "points": "1875,1711 1875,1771 2253,1771 2253,1711"
                },
                "text": "dissection/injection"
              }
            ]
          },
          {
            "id": "tr_1_tl_16",
            "coords": {
              "points": "297,1880 378,1910 458,1878 586,1900 1093,1878 1093,1826 1041,1801 1004,1828 789,1801 735,1826 564,1806 398,1831 297,1803"
            },
            "baseline": {
              "points": "310,1861 349,1860 389,1858 428,1861 468,1861 507,1861 547,1859 586,1860 626,1861 665,1860 705,1858 744,1858 784,1858 823,1858 863,1858 902,1858 942,1858 981,1858 1021,1858 1060,1858 1100,1858"
            },
            "text": "were either fresh or previously frozen.",
            "words": [
              {
                "id": "tr_1_tl_16_w1",
                "coords": {
                  "points": "302,1820 302,1880 389,1880 389,1820"
                },
                "text": "were"
              },
              {
                "id": "tr_1_tl_16_w2",
                "coords": {
                  "points": "410,1821 410,1881 523,1881 523,1821"
                },
                "text": "either"
              },
              {
                "id": "tr_1_tl_16_w3",
                "coords": {
                  "points": "544,1820 544,1880 631,1880 631,1820"
                },
                "text": "fresh"
              },
              {
                "id": "tr_1_tl_16_w4",
                "coords": {
                  "points": "663,1819 663,1879 699,1879 699,1819"
                },
                "text": "or"
              },
              {
                "id": "tr_1_tl_16_w5",
                "coords": {
                  "points": "715,1818 715,1878 926,1878 926,1818"
                },
                "text": "previously"
              },
              {
                "id": "tr_1_tl_16_w6",
                "coords": {
                  "points": "952,1818 952,1878 1091,1878 1091,1818"
                },
                "text": "frozen."
              }
            ]
          },
          {
            "id": "tr_1_tl_17",
            "coords": {
              "points": "440,1991 693,2021 1135,1967 1274,2006 1393,1962 1816,2021 2016,1964 2261,1981 2261,1910 2103,1917 2016,1873 1801,1922 1685,1880 1452,1930 1281,1887 1143,1925 569,1887 440,1922"
            },
            "baseline": {
              "points": "453,1960 543,1960 634,1960 725,1960 815,1960 906,1958 997,1957 1087,1957 1178,1957 1269,1957 1360,1954 1450,1954 1541,1954 1632,1954 1722,1951 1813,1954 1904,1951 1994,1951 2085,1951 2176,1951 2267,1948"
            },
            "text": "Two blackfin tuna, were caught on longline in the Gulf of Mexico and frozen before",
            "words": [
              {
                "id": "tr_1_tl_17_w1",
                "coords": {
                  "points": "442,1920 442,1980 520,1980 520,1920"
                },
                "text": "Two"
              },
              {
                "id": "tr_1_tl_17_w2",
                "coords": {
                  "points": "551,1920 551,1980 708,1980 708,1920"
                },
                "text": "blackfin"
              },
              {
                "id": "tr_1_tl_17_w3",
                "coords": {
                  "points": "745,1920 745,1980 842,1980 842,1920"
                },
                "text": "tuna,"
              },
              {
                "id": "tr_1_tl_17_w4",
                "coords": {
                  "points": "867,1917 867,1977 951,1977 951,1917"
                },
                "text": "were"
              },
              {
                "id": "tr_1_tl_17_w5",
                "coords": {
                  "points": "982,1917 982,1977 1115,1977 1115,1917"
                },
                "text": "caught"
              },
              {
                "id": "tr_1_tl_17_w6",
                "coords": {
                  "points": "1140,1917 1140,1977 1176,1977 1176,1917"
                },
                "text": "on"
              },
              {
                "id": "tr_1_tl_17_w7",
                "coords": {
                  "points": "1207,1916 1207,1976 1364,1976 1364,1916"
                },
                "text": "longline"
              },
              {
                "id": "tr_1_tl_17_w8",
                "coords": {
                  "points": "1395,1914 1395,1974 1425,1974 1425,1914"
                },
                "text": "in"
              },
              {
                "id": "tr_1_tl_17_w9",
                "coords": {
                  "points": "1456,1914 1456,1974 1503,1974 1503,1914"
                },
                "text": "the"
              },
              {
                "id": "tr_1_tl_17_w10",
                "coords": {
                  "points": "1535,1914 1535,1974 1626,1974 1626,1914"
                },
                "text": "Gulf"
              },
              {
                "id": "tr_1_tl_17_w11",
                "coords": {
                  "points": "1651,1912 1651,1972 1686,1972 1686,1912"
                },
                "text": "of"
              },
              {
                "id": "tr_1_tl_17_w12",
                "coords": {
                  "points": "1711,1913 1711,1973 1856,1973 1856,1913"
                },
                "text": "Mexico"
              },
              {
                "id": "tr_1_tl_17_w13",
                "coords": {
                  "points": "1887,1911 1887,1971 1948,1971 1948,1911"
                },
                "text": "and"
              },
              {
                "id": "tr_1_tl_17_w14",
                "coords": {
                  "points": "1979,1911 1979,1971 2099,1971 2099,1911"
                },
                "text": "frozen"
              },
              {
                "id": "tr_1_tl_17_w15",
                "coords": {
                  "points": "2130,1910 2130,1970 2251,1970 2251,1910"
                },
                "text": "before"
              }
            ]
          },
          {
            "id": "tr_1_tl_18",
            "coords": {
              "points": "289,2135 314,2130 344,2105 396,2130 450,2088 475,2095 515,2132 534,2132 534,1994 428,1989 408,2006 378,2006 322,1991 289,2004"
            },
            "baseline": {
              "points": "304,2058 329,2060 355,2061 381,2061 407,2061 433,2061 459,2061 485,2061 511,2061 537,2061"
            },
            "text": "dissection.",
            "words": [
              {
                "id": "tr_1_tl_18_w1",
                "coords": {
                  "points": "294,2021 294,2081 521,2081 521,2021"
                },
                "text": "dissection."
              }
            ]
          },
          {
            "id": "tr_1_tl_19",
            "coords": {
              "points": "284,2278 341,2296 366,2278 396,2283 435,2308 472,2288 539,2298 609,2271 693,2296 695,2179 660,2172 562,2221 512,2194 443,2226 361,2172 284,2224"
            },
            "baseline": {
              "points": "298,2261 323,2261 348,2261 373,2261 398,2261 423,2261 448,2261 473,2261 498,2261 523,2261 548,2259 573,2258 598,2258 623,2258 648,2258 673,2258 698,2258"
            },
            "text": "Silicon Injections",
            "words": [
              {
                "id": "tr_1_tl_19_w1",
                "coords": {
                  "points": "291,2221 291,2281 432,2281 432,2221"
                },
                "text": "Silicon"
              },
              {
                "id": "tr_1_tl_19_w2",
                "coords": {
                  "points": "462,2218 462,2278 680,2278 680,2218"
                },
                "text": "Injections"
              }
            ]
          },
          {
            "id": "tr_1_tl_20",
            "coords": {
              "points": "440,2380 1531,2362 1645,2414 1860,2367 2268,2367 2268,2301 2172,2263 2038,2318 1833,2268 1640,2306 1576,2266 1217,2318 440,2313"
            },
            "baseline": {
              "points": "453,2357 544,2360 635,2357 726,2357 817,2357 908,2357 999,2357 1090,2357 1181,2354 1272,2354 1363,2354 1454,2352 1545,2352 1636,2354 1727,2352 1818,2351 1909,2351 2000,2351 2091,2351 2182,2348 2273,2348"
            },
            "text": "Injections were performed using Microfil injection compounds MV-120 (blue), MV-130",
            "words": [
              {
                "id": "tr_1_tl_20_w1",
                "coords": {
                  "points": "442,2319 442,2379 637,2379 637,2319"
                },
                "text": "Injections"
              },
              {
                "id": "tr_1_tl_20_w2",
                "coords": {
                  "points": "657,2317 657,2377 751,2377 751,2317"
                },
                "text": "were"
              },
              {
                "id": "tr_1_tl_20_w3",
                "coords": {
                  "points": "777,2317 777,2377 973,2377 973,2317"
                },
                "text": "performed"
              },
              {
                "id": "tr_1_tl_20_w4",
                "coords": {
                  "points": "999,2317 999,2377 1099,2377 1099,2317"
                },
                "text": "using"
              },
              {
                "id": "tr_1_tl_20_w5",
                "coords": {
                  "points": "1125,2314 1125,2374 1296,2374 1296,2314"
                },
                "text": "Microfil"
              },
              {
                "id": "tr_1_tl_20_w6",
                "coords": {
                  "points": "1309,2313 1309,2373 1472,2373 1472,2313"
                },
                "text": "injection"
              },
              {
                "id": "tr_1_tl_20_w7",
                "coords": {
                  "points": "1505,2313 1505,2373 1732,2373 1732,2313"
                },
                "text": "compounds"
              },
              {
                "id": "tr_1_tl_20_w8",
                "coords": {
                  "points": "1752,2311 1752,2371 1915,2371 1915,2311"
                },
                "text": "MV-120"
              },
              {
                "id": "tr_1_tl_20_w9",
                "coords": {
                  "points": "1942,2311 1942,2371 2080,2371 2080,2311"
                },
                "text": "(blue),"
              },
              {
                "id": "tr_1_tl_20_w10",
                "coords": {
                  "points": "2094,2308 2094,2368 2257,2368 2257,2308"
                },
                "text": "MV-130"
              }
            ]
          },
          {
            "id": "tr_1_tl_21",
            "coords": {
              "points": "294,2469 777,2471 888,2516 1202,2464 1469,2464 1608,2516 2110,2459 2278,2498 2281,2397 294,2429"
            },
            "baseline": {
              "points": "307,2458 405,2458 504,2458 603,2455 702,2457 801,2458 900,2458 999,2455 1098,2455 1197,2453 1296,2455 1394,2455 1493,2452 1592,2452 1691,2452 1790,2452 1889,2452 1988,2452 2087,2449 2186,2449 2285,2449"
            },
            "text": "(red) and MV-117 (orange). Components were mixed in a 5 (color): 4 (diluent): 1 (catalyst)",
            "words": [
              {
                "id": "tr_1_tl_21_w1",
                "coords": {
                  "points": "302,2418 302,2478 398,2478 398,2418"
                },
                "text": "(red)"
              },
              {
                "id": "tr_1_tl_21_w2",
                "coords": {
                  "points": "416,2418 416,2478 476,2478 476,2418"
                },
                "text": "and"
              },
              {
                "id": "tr_1_tl_21_w3",
                "coords": {
                  "points": "507,2415 507,2475 669,2475 669,2415"
                },
                "text": "MV-117"
              },
              {
                "id": "tr_1_tl_21_w4",
                "coords": {
                  "points": "719,2418 719,2478 905,2478 905,2418"
                },
                "text": "(orange)."
              },
              {
                "id": "tr_1_tl_21_w5",
                "coords": {
                  "points": "936,2415 936,2475 1189,2475 1189,2415"
                },
                "text": "Components"
              },
              {
                "id": "tr_1_tl_21_w6",
                "coords": {
                  "points": "1214,2414 1214,2474 1298,2474 1298,2414"
                },
                "text": "were"
              },
              {
                "id": "tr_1_tl_21_w7",
                "coords": {
                  "points": "1329,2415 1329,2475 1443,2475 1443,2415"
                },
                "text": "mixed"
              },
              {
                "id": "tr_1_tl_21_w8",
                "coords": {
                  "points": "1474,2412 1474,2472 1497,2472 1497,2412"
                },
                "text": "in"
              },
              {
                "id": "tr_1_tl_21_w9",
                "coords": {
                  "points": "1528,2412 1528,2472 1540,2472 1540,2412"
                },
                "text": "a"
              },
              {
                "id": "tr_1_tl_21_w10",
                "coords": {
                  "points": "1571,2412 1571,2472 1582,2472 1582,2412"
                },
                "text": "5"
              },
              {
                "id": "tr_1_tl_21_w11",
                "coords": {
                  "points": "1613,2412 1613,2472 1763,2472 1763,2412"
                },
                "text": "(color):"
              },
              {
                "id": "tr_1_tl_21_w12",
                "coords": {
                  "points": "1782,2412 1782,2472 1793,2472 1793,2412"
                },
                "text": "4"
              },
              {
                "id": "tr_1_tl_21_w13",
                "coords": {
                  "points": "1824,2412 1824,2472 2011,2472 2011,2412"
                },
                "text": "(diluent):"
              },
              {
                "id": "tr_1_tl_21_w14",
                "coords": {
                  "points": "2036,2410 2036,2470 2053,2470 2053,2410"
                },
                "text": "1"
              },
              {
                "id": "tr_1_tl_21_w15",
                "coords": {
                  "points": "2072,2409 2072,2469 2265,2469 2265,2409"
                },
                "text": "(catalyst)"
              }
            ]
          },
          {
            "id": "tr_1_tl_22",
            "coords": {
              "points": "294,2595 668,2610 769,2575 967,2615 1375,2568 1603,2607 1781,2565 1959,2607 2071,2560 2276,2570 2244,2501 1925,2518 1761,2476 1452,2523 544,2496 294,2531"
            },
            "baseline": {
              "points": "307,2562 405,2559 504,2559 603,2559 702,2556 800,2559 899,2556 998,2556 1097,2553 1195,2555 1294,2553 1393,2553 1492,2553 1590,2553 1689,2553 1788,2551 1887,2551 1985,2551 2084,2551 2183,2551 2282,2553"
            },
            "text": "ratio. Curing time was approximately twenty minutes depending on the core temperature of each",
            "words": [
              {
                "id": "tr_1_tl_22_w1",
                "coords": {
                  "points": "295,2520 295,2580 404,2580 404,2520"
                },
                "text": "ratio."
              },
              {
                "id": "tr_1_tl_22_w2",
                "coords": {
                  "points": "428,2519 428,2579 555,2579 555,2519"
                },
                "text": "Curing"
              },
              {
                "id": "tr_1_tl_22_w3",
                "coords": {
                  "points": "584,2518 584,2578 659,2578 659,2518"
                },
                "text": "time"
              },
              {
                "id": "tr_1_tl_22_w4",
                "coords": {
                  "points": "683,2516 683,2576 757,2576 757,2516"
                },
                "text": "was"
              },
              {
                "id": "tr_1_tl_22_w5",
                "coords": {
                  "points": "781,2516 781,2576 1058,2576 1058,2516"
                },
                "text": "approximately"
              },
              {
                "id": "tr_1_tl_22_w6",
                "coords": {
                  "points": "1082,2513 1082,2573 1203,2573 1203,2513"
                },
                "text": "twenty"
              },
              {
                "id": "tr_1_tl_22_w7",
                "coords": {
                  "points": "1232,2513 1232,2573 1382,2573 1382,2513"
                },
                "text": "minutes"
              },
              {
                "id": "tr_1_tl_22_w8",
                "coords": {
                  "points": "1406,2513 1406,2573 1602,2573 1602,2513"
                },
                "text": "depending"
              },
              {
                "id": "tr_1_tl_22_w9",
                "coords": {
                  "points": "1626,2513 1626,2573 1660,2573 1660,2513"
                },
                "text": "on"
              },
              {
                "id": "tr_1_tl_22_w10",
                "coords": {
                  "points": "1690,2512 1690,2572 1741,2572 1741,2512"
                },
                "text": "the"
              },
              {
                "id": "tr_1_tl_22_w11",
                "coords": {
                  "points": "1765,2511 1765,2571 1839,2571 1839,2511"
                },
                "text": "core"
              },
              {
                "id": "tr_1_tl_22_w12",
                "coords": {
                  "points": "1863,2511 1863,2571 2094,2571 2094,2511"
                },
                "text": "temperature"
              },
              {
                "id": "tr_1_tl_22_w13",
                "coords": {
                  "points": "2118,2511 2118,2571 2157,2571 2157,2511"
                },
                "text": "of"
              },
              {
                "id": "tr_1_tl_22_w14",
                "coords": {
                  "points": "2176,2511 2176,2571 2250,2571 2250,2511"
                },
                "text": "each"
              }
            ]
          },
          {
            "id": "tr_1_tl_23",
            "coords": {
              "points": "297,2714 411,2726 651,2674 824,2711 888,2677 985,2721 1046,2679 1190,2664 1190,2610 1106,2588 980,2622 868,2588 782,2622 623,2600 539,2630 297,2597"
            },
            "baseline": {
              "points": "310,2658 354,2658 398,2658 442,2658 487,2658 531,2658 575,2658 620,2658 664,2658 708,2658 753,2655 797,2658 841,2658 885,2658 930,2655 974,2655 1018,2655 1063,2655 1107,2655 1151,2655 1196,2655"
            },
            "text": "fish and the ambient temperature in the lab.",
            "words": [
              {
                "id": "tr_1_tl_23_w1",
                "coords": {
                  "points": "302,2618 302,2678 362,2678 362,2618"
                },
                "text": "fish"
              },
              {
                "id": "tr_1_tl_23_w2",
                "coords": {
                  "points": "388,2618 388,2678 449,2678 449,2618"
                },
                "text": "and"
              },
              {
                "id": "tr_1_tl_23_w3",
                "coords": {
                  "points": "475,2618 475,2678 526,2678 526,2618"
                },
                "text": "the"
              },
              {
                "id": "tr_1_tl_23_w4",
                "coords": {
                  "points": "552,2618 552,2678 714,2678 714,2618"
                },
                "text": "ambient"
              },
              {
                "id": "tr_1_tl_23_w5",
                "coords": {
                  "points": "730,2618 730,2678 964,2678 964,2618"
                },
                "text": "temperature"
              },
              {
                "id": "tr_1_tl_23_w6",
                "coords": {
                  "points": "990,2615 990,2675 1010,2675 1010,2615"
                },
                "text": "in"
              },
              {
                "id": "tr_1_tl_23_w7",
                "coords": {
                  "points": "1041,2615 1041,2675 1091,2675 1091,2615"
                },
                "text": "the"
              },
              {
                "id": "tr_1_tl_23_w8",
                "coords": {
                  "points": "1112,2615 1112,2675 1188,2675 1188,2615"
                },
                "text": "lab."
              }
            ]
          },
          {
            "id": "tr_1_tl_24",
            "coords": {
              "points": "445,2768 1108,2768 1343,2815 1507,2766 2122,2803 2261,2771 2261,2699 2192,2682 1873,2716 1781,2682 1630,2733 928,2689 445,2714"
            },
            "baseline": {
              "points": "459,2756 549,2754 639,2755 729,2753 820,2756 910,2753 1000,2753 1090,2753 1181,2753 1271,2753 1361,2753 1451,2753 1542,2750 1632,2750 1722,2750 1812,2750 1903,2750 1993,2750 2083,2747 2173,2747 2264,2747"
            },
            "text": "The desired vessels were first found through dissection. A catheter attached to a Cole-",
            "words": [
              {
                "id": "tr_1_tl_24_w1",
                "coords": {
                  "points": "446,2715 446,2775 512,2775 512,2715"
                },
                "text": "The"
              },
              {
                "id": "tr_1_tl_24_w2",
                "coords": {
                  "points": "540,2714 540,2774 673,2774 673,2714"
                },
                "text": "desired"
              },
              {
                "id": "tr_1_tl_24_w3",
                "coords": {
                  "points": "707,2714 707,2774 845,2774 845,2714"
                },
                "text": "vessels"
              },
              {
                "id": "tr_1_tl_24_w4",
                "coords": {
                  "points": "868,2713 868,2773 956,2773 956,2713"
                },
                "text": "were"
              },
              {
                "id": "tr_1_tl_24_w5",
                "coords": {
                  "points": "985,2713 985,2773 1062,2773 1062,2713"
                },
                "text": "first"
              },
              {
                "id": "tr_1_tl_24_w6",
                "coords": {
                  "points": "1079,2713 1079,2773 1190,2773 1190,2713"
                },
                "text": "found"
              },
              {
                "id": "tr_1_tl_24_w7",
                "coords": {
                  "points": "1213,2713 1213,2773 1363,2773 1363,2713"
                },
                "text": "through"
              },
              {
                "id": "tr_1_tl_24_w8",
                "coords": {
                  "points": "1391,2711 1391,2771 1608,2771 1608,2711"
                },
                "text": "dissection."
              },
              {
                "id": "tr_1_tl_24_w9",
                "coords": {
                  "points": "1642,2710 1642,2770 1658,2770 1658,2710"
                },
                "text": "A"
              },
              {
                "id": "tr_1_tl_24_w10",
                "coords": {
                  "points": "1692,2710 1692,2770 1852,2770 1852,2710"
                },
                "text": "catheter"
              },
              {
                "id": "tr_1_tl_24_w11",
                "coords": {
                  "points": "1875,2710 1875,2770 2030,2770 2030,2710"
                },
                "text": "attached"
              },
              {
                "id": "tr_1_tl_24_w12",
                "coords": {
                  "points": "2059,2707 2059,2767 2086,2767 2086,2707"
                },
                "text": "to"
              },
              {
                "id": "tr_1_tl_24_w13",
                "coords": {
                  "points": "2114,2707 2114,2767 2130,2767 2130,2707"
                },
                "text": "a"
              },
              {
                "id": "tr_1_tl_24_w14",
                "coords": {
                  "points": "2153,2707 2153,2767 2264,2767 2264,2707"
                },
                "text": "Cole-"
              }
            ]
          },
          {
            "id": "tr_1_tl_25",
            "coords": {
              "points": "289,2907 512,2867 1086,2914 1432,2865 2271,2889 2271,2795 2177,2776 1769,2815 1596,2783 1422,2820 289,2810"
            },
            "baseline": {
              "points": "304,2858 402,2855 501,2856 599,2855 698,2855 797,2855 895,2855 994,2855 1092,2855 1191,2855 1290,2852 1388,2852 1487,2851 1585,2852 1684,2849 1783,2849 1881,2849 1980,2849 2078,2849 2177,2849 2276,2849"
            },
            "text": "Pamer three-way stopcock was inserted as far as possible into the vessel of choice and the",
            "words": [
              {
                "id": "tr_1_tl_25_w1",
                "coords": {
                  "points": "296,2816 296,2876 417,2876 417,2816"
                },
                "text": "Pamer"
              },
              {
                "id": "tr_1_tl_25_w2",
                "coords": {
                  "points": "441,2815 441,2875 644,2875 644,2815"
                },
                "text": "three-way"
              },
              {
                "id": "tr_1_tl_25_w3",
                "coords": {
                  "points": "674,2815 674,2875 847,2875 847,2815"
                },
                "text": "stopcock"
              },
              {
                "id": "tr_1_tl_25_w4",
                "coords": {
                  "points": "878,2815 878,2875 953,2875 953,2815"
                },
                "text": "was"
              },
              {
                "id": "tr_1_tl_25_w5",
                "coords": {
                  "points": "977,2815 977,2875 1133,2875 1133,2815"
                },
                "text": "inserted"
              },
              {
                "id": "tr_1_tl_25_w6",
                "coords": {
                  "points": "1169,2815 1169,2875 1203,2875 1203,2815"
                },
                "text": "as"
              },
              {
                "id": "tr_1_tl_25_w7",
                "coords": {
                  "points": "1227,2813 1227,2873 1278,2873 1278,2813"
                },
                "text": "far"
              },
              {
                "id": "tr_1_tl_25_w8",
                "coords": {
                  "points": "1302,2812 1302,2872 1342,2872 1342,2812"
                },
                "text": "as"
              },
              {
                "id": "tr_1_tl_25_w9",
                "coords": {
                  "points": "1366,2811 1366,2871 1529,2871 1529,2811"
                },
                "text": "possible"
              },
              {
                "id": "tr_1_tl_25_w10",
                "coords": {
                  "points": "1559,2811 1559,2871 1627,2871 1627,2811"
                },
                "text": "into"
              },
              {
                "id": "tr_1_tl_25_w11",
                "coords": {
                  "points": "1657,2809 1657,2869 1715,2869 1715,2809"
                },
                "text": "the"
              },
              {
                "id": "tr_1_tl_25_w12",
                "coords": {
                  "points": "1745,2809 1745,2869 1872,2869 1872,2809"
                },
                "text": "vessel"
              },
              {
                "id": "tr_1_tl_25_w13",
                "coords": {
                  "points": "1890,2809 1890,2869 1930,2869 1930,2809"
                },
                "text": "of"
              },
              {
                "id": "tr_1_tl_25_w14",
                "coords": {
                  "points": "1954,2809 1954,2869 2082,2869 2082,2809"
                },
                "text": "choice"
              },
              {
                "id": "tr_1_tl_25_w15",
                "coords": {
                  "points": "2111,2809 2111,2869 2175,2869 2175,2809"
                },
                "text": "and"
              },
              {
                "id": "tr_1_tl_25_w16",
                "coords": {
                  "points": "2204,2809 2204,2869 2262,2869 2262,2809"
                },
                "text": "the"
              }
            ]
          },
          {
            "id": "tr_1_tl_26",
            "coords": {
              "points": "289,2998 745,2973 918,3006 1017,2968 1321,3003 1393,2956 1714,2996 2031,2961 2271,3013 2271,2894 942,2924 861,2887 754,2926 418,2889 289,2929"
            },
            "baseline": {
              "points": "304,2959 402,2959 501,2957 599,2956 698,2954 797,2956 895,2956 994,2954 1092,2954 1191,2953 1290,2953 1388,2950 1487,2952 1585,2950 1684,2952 1783,2950 1881,2950 1980,2950 2078,2950 2177,2950 2276,2947"
            },
            "text": "system was flushed with sea water in order to rinse out blood and test for leaks or blockages.",
            "words": [
              {
                "id": "tr_1_tl_26_w1",
                "coords": {
                  "points": "290,2919 290,2979 408,2979 408,2919"
                },
                "text": "system"
              },
              {
                "id": "tr_1_tl_26_w2",
                "coords": {
                  "points": "450,2917 450,2977 527,2977 527,2917"
                },
                "text": "was"
              },
              {
                "id": "tr_1_tl_26_w3",
                "coords": {
                  "points": "551,2915 551,2975 688,2975 688,2915"
                },
                "text": "flushed"
              },
              {
                "id": "tr_1_tl_26_w4",
                "coords": {
                  "points": "718,2915 718,2975 800,2975 800,2915"
                },
                "text": "with"
              },
              {
                "id": "tr_1_tl_26_w5",
                "coords": {
                  "points": "831,2916 831,2976 883,2976 883,2916"
                },
                "text": "sea"
              },
              {
                "id": "tr_1_tl_26_w6",
                "coords": {
                  "points": "908,2914 908,2974 1020,2974 1020,2914"
                },
                "text": "water"
              },
              {
                "id": "tr_1_tl_26_w7",
                "coords": {
                  "points": "1044,2914 1044,2974 1067,2974 1067,2914"
                },
                "text": "in"
              },
              {
                "id": "tr_1_tl_26_w8",
                "coords": {
                  "points": "1098,2913 1098,2973 1198,2973 1198,2913"
                },
                "text": "order"
              },
              {
                "id": "tr_1_tl_26_w9",
                "coords": {
                  "points": "1223,2913 1223,2973 1252,2973 1252,2913"
                },
                "text": "to"
              },
              {
                "id": "tr_1_tl_26_w10",
                "coords": {
                  "points": "1276,2912 1276,2972 1364,2972 1364,2912"
                },
                "text": "rinse"
              },
              {
                "id": "tr_1_tl_26_w11",
                "coords": {
                  "points": "1395,2910 1395,2970 1459,2970 1459,2910"
                },
                "text": "out"
              },
              {
                "id": "tr_1_tl_26_w12",
                "coords": {
                  "points": "1472,2911 1472,2971 1585,2971 1585,2911"
                },
                "text": "blood"
              },
              {
                "id": "tr_1_tl_26_w13",
                "coords": {
                  "points": "1615,2911 1615,2971 1673,2971 1673,2911"
                },
                "text": "and"
              },
              {
                "id": "tr_1_tl_26_w14",
                "coords": {
                  "points": "1698,2911 1698,2971 1768,2971 1768,2911"
                },
                "text": "test"
              },
              {
                "id": "tr_1_tl_26_w15",
                "coords": {
                  "points": "1787,2910 1787,2970 1845,2970 1845,2910"
                },
                "text": "for"
              },
              {
                "id": "tr_1_tl_26_w16",
                "coords": {
                  "points": "1864,2910 1864,2970 1965,2970 1965,2910"
                },
                "text": "leaks"
              },
              {
                "id": "tr_1_tl_26_w17",
                "coords": {
                  "points": "1989,2910 1989,2970 2030,2970 2030,2910"
                },
                "text": "or"
              },
              {
                "id": "tr_1_tl_26_w18",
                "coords": {
                  "points": "2049,2910 2049,2970 2267,2970 2267,2910"
                },
                "text": "blockages."
              }
            ]
          }
        ]
      }
    ]
  }
}